upd_slash_command/__init__.py
upd_slash_command-0.1.1.dist-info/METADATA
upd_slash_command-0.1.1.dist-info/WHEEL
upd_slash_command-0.1.1.dist-info/RECORD
