Metadata-Version: 2.4
Name: upd-slash-command
Version: 0.1.1
Summary: CLI tool for updating Claude Code slash commands from git.
Project-URL: Repository, https://upd.dev/skills/agent-skills-project
License-Expression: MIT
Keywords: agent,ai,claude,claude-code,slash-command
Requires-Python: >=3.10
